pyreaddbc/__init__.py
pyreaddbc/_build_readdbc.py
pyreaddbc/_readdbc.c
pyreaddbc/_readdbc.so
pyreaddbc/blast.c
pyreaddbc/blast.h
pyreaddbc/c-src/__init__.py
pyreaddbc/c-src/blast.c
pyreaddbc/c-src/blast.h
pyreaddbc/c-src/dbc2dbf.c
pyreaddbc/readdbc.py
pyreaddbc-1.1.0.dist-info/LICENSE
pyreaddbc-1.1.0.dist-info/METADATA
pyreaddbc-1.1.0.dist-info/WHEEL
pyreaddbc-1.1.0.dist-info/RECORD
