Metadata-Version: 2.1
Name: pyreaddbc
Version: 1.1.0
Summary: pyreaddbc package
Home-page: https://github.com/osl-incubator/pyreaddbc
License: AGPL-3.0
Author: Flavio Codeco Coelho
Author-email: fccoelho@gmail.com
Requires-Python: >=3.9,<4
Classifier: Development Status :: 3 - Alpha
Classifier: Intended Audience :: Developers
Classifier: License :: OSI Approved :: GNU Affero General Public License v3
Classifier: License :: OSI Approved :: GNU Affero General Public License v3 or later (AGPLv3+)
Classifier: Operating System :: OS Independent
Classifier: Programming Language :: Python :: 3
Classifier: Programming Language :: Python :: 3.9
Classifier: Programming Language :: Python :: 3.10
Classifier: Programming Language :: Python :: 3.11
Classifier: Topic :: Software Development :: Libraries :: Python Modules
Requires-Dist: cffi (>=1.15.1,<2)
Requires-Dist: dbfread (>=2.0.7,<3)
Requires-Dist: pandas (>=1.4.3,<2)
Requires-Dist: pyyaml (>=6)
Requires-Dist: tqdm (>=4.64.0,<5)
Project-URL: Repository, https://github.com/osl-incubator/pyreaddbc
